{
  "posts": [
    {
      "title": "Eclipse 라이브",
      "coupon": "SPECIALONAIR",
      "link": null,
      "reward": [
        {
          "name": "숙명의 쿠키커터",
          "quantity": 15,
          "imgUrl": "https://www.sk2gacha.com/_next/image?url=https%3A%2F%2Fsugar-gnome-warehouse-img.org%2Fimages%2F1749386510479-o9heof.webp&w=96&q=75"
        },
        {
          "name": "크리스탈",
          "quantity": 5000,
          "imgUrl": "https://www.sk2gacha.com/_next/image?url=https%3A%2F%2Fsugar-gnome-warehouse-img.org%2Fimages%2F1749386511862-6ngij4.webp&w=96&q=75"
        },
        {
          "name": "무지개 큐브",
          "quantity": 4500,
          "imgUrl": "https://www.sk2gacha.com/_next/image?url=https%3A%2F%2Fsugar-gnome-warehouse-img.org%2Fimages%2F1749386467842-swrh1i.webp&w=96&q=75"
        },
        {
          "name": "빛나는 비스킷 도우",
          "quantity": 200,
          "imgUrl": "https://www.sk2gacha.com/_next/image?url=https%3A%2F%2Fsugar-gnome-warehouse-img.org%2Fimages%2F1749386510994-u5ijko.webp&w=96&q=75"
        },
        {
          "name": "버터호박석",
          "quantity": 3,
          "imgUrl": "https://www.sk2gacha.com/_next/image?url=https%3A%2F%2Fsugar-gnome-warehouse-img.org%2Fimages%2F2025-09-19T22-30-44-119_4v2a03.webp&w=96&q=75"
        }
      ]
    },
    {
      "title": "miss earthbread",
      "coupon": "MISSEARTHBREAD25",
      "link": null,
      "reward": [
        {
          "name": "크리스탈",
          "quantity": 3000,
          "imgUrl": "https://www.sk2gacha.com/_next/image?url=https%3A%2F%2Fsugar-gnome-warehouse-img.org%2Fimages%2F1749386511862-6ngij4.webp&w=96&q=75"
        },
        {
          "name": "무지개 큐브",
          "quantity": 1500,
          "imgUrl": "https://www.sk2gacha.com/_next/image?url=https%3A%2F%2Fsugar-gnome-warehouse-img.org%2Fimages%2F1749386467842-swrh1i.webp&w=96&q=75"
        },
        {
          "name": "초코정크 초크",
          "quantity": 1000,
          "imgUrl": "https://www.sk2gacha.com/_next/image?url=https%3A%2F%2Fsugar-gnome-warehouse-img.org%2Fimages%2F1749386509314-mm0sz8.webp&w=96&q=75"
        }
      ]
    }
  ]
}